{
    "max_seq_length": 512,
    "vocab_size": 30522,
    "model_size": "small",
    "train_batch_size":128,
    "embedding_size":256,
    "do_train": true,
    "save_checkpoints_steps": 100000,
    "electric_objective": false,
    "electra_objective":false,
    "two_tower_generator": false,
    "tta_generator": true,
    "electra_nce_objective":true,
    "untied_generator_embeddings":false,
    "untied_generator": true,
    "use_pretrained_generator":false,
    "use_pretrained_discriminator":false,
    "logits_temp": 1.0,
    "gumbel_temp": 0.1,
    "monitoring":true,
    "straight_through": true,
    "model_scope":"electra",
    "disallow_correct":false,
    "tpu_name":"albert1",
    "use_tpu":true,
    "num_tpu_cores":8,
    "disc_weight":1.0,
    "electra_disc_weight":1.0,
    "nce_disc_weight":1.0,
    "lr_decay_power":1.0,
    "logprob_avg":false,
    "num_train_steps":1000000,
    "learning_rate":1e-4,
    "generator_hidden_size":0.25,
    "model_size_generator":"tiny_512",
    "nce":"nce",
    "mask_strategy":"electra",
    "stage":"one_stage",
    "gen_learning_rate":1e-4,
    "disc_learning_rate":1e-4,
    "mask_prob":0.5,
    "stop_gradient": false,
    "final_ratio":0.2,
    "initial_ratio":0.5,
    "leak_ratio":0.0,
    "rand_ratio":0.0,
    "nce_electra":true,
    "spectral_regularization":false,
    "fake_data_sample":"sample_from_softmax",
    "topk":20,
    "generator_embedding_size": 256
}
